MANIFEST.in
README.md
setup.py
ct_manager/__init__.py
ct_manager/api.py
ct_manager/api_example.py
ct_manager/base_handler.py
ct_manager/config.yaml
ct_manager/const.py
ct_manager/email_handler.py
ct_manager/enums.py
ct_manager/models.py
ct_manager/remote_handler.py
ct_manager/settings.py
ct_manager.egg-info/PKG-INFO
ct_manager.egg-info/SOURCES.txt
ct_manager.egg-info/dependency_links.txt
ct_manager.egg-info/requires.txt
ct_manager.egg-info/top_level.txt
ct_manager/oracle/__init__.py
ct_manager/oracle/oracle_datahandler.py
ct_manager/pg/__init__.py
ct_manager/pg/pg_handler.py
ct_manager/pg/models/__init__.py
ct_manager/pg/models/equity_index_futures_models.py
ct_manager/pg/models/index_models.py
ct_manager/pg/models/industry_models.py
ct_manager/pg/models/ptf_models.py
ct_manager/pg/models/ramp_status_models.py
ct_manager/pg/models/record_model.py
ct_manager/pg/models/risk_models.py
ct_manager/pg/models/stock_models.py
ct_manager/pg/models/strat_models.py
ct_manager/pg/models/uqer_models.py
ct_manager/tests/__init__.py
ct_manager/tests/test_api_function.py
ct_manager/tests/test_suite.py
ct_manager/tests/test_utils.py
ct_manager/tushare/__init__.py
ct_manager/tushare/tushare_handler.py
ct_manager/uqer/__init__.py
ct_manager/uqer/uqer_handler.py
ct_manager/utils/__init__.py
ct_manager/utils/date_utils.py
requirements/py2.txt
requirements/py3.txt