Metadata-Version: 1.1
Name: ct-manager
Version: 1.0.9
Summary: data manager
Home-page: https://github.com/iLampard/ct_manager
Author: iLampard, MarkSh714, Bella21
Author-email: UNKNOWN
License: UNKNOWN
Platform: UNKNOWN
Classifier: Programming Language :: Python
Classifier: Programming Language :: Python :: 2.7
Classifier: Programming Language :: Python :: 3.5
Classifier: Programming Language :: Python :: 3.6
